pycentraldispatch/__init__.py
pycentraldispatch/py_central_dispatch.py
pycentraldispatch/thread_pool.py
pycentraldispatch-1.0.11.dist-info/LICENSE
pycentraldispatch-1.0.11.dist-info/METADATA
pycentraldispatch-1.0.11.dist-info/WHEEL
pycentraldispatch-1.0.11.dist-info/top_level.txt
pycentraldispatch-1.0.11.dist-info/RECORD
