Metadata-Version: 2.1
Name: pycentraldispatch
Version: 1.0.11
Summary: A simple Grand Central Dispatch (GCD) inspired API for python.
Home-page: https://github.com/mrhappyasthma/PyCentralDispatch
Author: MrHappyAsthma
Author-email: mrhappyasthma@gmail.com
License: UNKNOWN
Platform: UNKNOWN
Classifier: Programming Language :: Python :: 3
Classifier: License :: OSI Approved :: MIT License
Classifier: Operating System :: OS Independent
Requires-Python: >=3.6
